icemac.ab.importxls-2.5-py2.7-nspkg.pth
icemac/ab/importxls/__init__.py
icemac/ab/importxls/configure.zcml
icemac/ab/importxls/xls.py
icemac/ab/importxls/tests/__init__.py
icemac/ab/importxls/tests/test_xls.py
icemac/ab/importxls/tests/data/edge.xls
icemac/ab/importxls/tests/data/long.xls
icemac/ab/importxls/tests/data/short.xls
icemac.ab.importxls-2.5.dist-info/DESCRIPTION.rst
icemac.ab.importxls-2.5.dist-info/METADATA
icemac.ab.importxls-2.5.dist-info/RECORD
icemac.ab.importxls-2.5.dist-info/WHEEL
icemac.ab.importxls-2.5.dist-info/metadata.json
icemac.ab.importxls-2.5.dist-info/namespace_packages.txt
icemac.ab.importxls-2.5.dist-info/top_level.txt
