Metadata-Version: 2.0
Name: icemac.ab.importxls
Version: 2.5
Summary: Import XLS files into icemac.addressbook.
Home-page: https://pypi.org/project/icemac.ab.importxls
Author: Michael Howitz
Author-email: icemac@gmx.net
License: MIT
Keywords: icemac.addressbook xls excel import
Platform: UNKNOWN
Classifier: Development Status :: 5 - Production/Stable
Classifier: Environment :: Web Environment
Classifier: Framework :: Zope3
Classifier: License :: OSI Approved :: MIT License
Classifier: Natural Language :: English
Classifier: Operating System :: OS Independent
Classifier: Programming Language :: Python :: 2.7
Classifier: Programming Language :: Python :: 2 :: Only
Provides-Extra: test
Requires-Dist: icemac.ab.importer (>=1.0)
Requires-Dist: setuptools
Requires-Dist: xlrd
Provides-Extra: test
Requires-Dist: zope.testing (>=3.8.0); extra == 'test'
